windoweasy/__init__.py
windoweasy/windoweasy.py
windoweasy-0.1.4.dist-info/LICENSE.txt
windoweasy-0.1.4.dist-info/METADATA
windoweasy-0.1.4.dist-info/WHEEL
windoweasy-0.1.4.dist-info/top_level.txt
windoweasy-0.1.4.dist-info/RECORD
