Metadata-Version: 2.1
Name: windoweasy
Version: 0.1.4
Summary: windoweasy is a simple and user-friendly library built on top of Pygame, providing easy window creation and basic drawing functions for game development and graphical applications
Home-page: https://pypi.org/user/INTERJL/
Author: INTERJL
Author-email: makar.arapov.real@gmail.ru
Project-URL: GitHub, https://github.com/INTERJL
Keywords: window screen games game
Classifier: Programming Language :: Python :: 3.11
Classifier: License :: OSI Approved :: MIT License
Classifier: Operating System :: OS Independent
Requires-Python: >=3.6
License-File: LICENSE.txt
Requires-Dist: requests (>=2.25.1)
